LICENSE
README.md
setup.cfg
setup.py
problem180meridian/__init__.py
problem180meridian/get_coordinates.py
problem180meridian/polygonhierarchy.py
problem180meridian/split180meridian.py
problem180meridian.egg-info/PKG-INFO
problem180meridian.egg-info/SOURCES.txt
problem180meridian.egg-info/dependency_links.txt
problem180meridian.egg-info/requires.txt
problem180meridian.egg-info/top_level.txt
test/test_PolygonHierarchy.py
test/test_cross180.py
test/test_points_from_geometry.py
test/test_points_from_wkt.py
test/test_split180_geometry.py
test/test_split180_multilinestring.py
test/test_split180_multipolygon.py